rak_tools/CodeEditor.py
rak_tools/FileList.py
rak_tools/HTML_Report.py
rak_tools/__init__.py
rak_tools-0.5.7.dist-info/LICENSE
rak_tools-0.5.7.dist-info/METADATA
rak_tools-0.5.7.dist-info/WHEEL
rak_tools-0.5.7.dist-info/top_level.txt
rak_tools-0.5.7.dist-info/RECORD
