Metadata-Version: 2.1
Name: rak-tools
Version: 0.5.7
Summary: UI package for lightras tools
Home-page: UNKNOWN
Author: marvinYu
Author-email: marvin_ywf@163.com
License: UNKNOWN
Platform: UNKNOWN
Classifier: Programming Language :: Python :: 3
Classifier: Operating System :: OS Independent
Requires-Python: >=3.6
Requires-Dist: wxPython (>=4.1.0)
